flatten_any_dict_iterable_or_whatsoever/LICENSE
flatten_any_dict_iterable_or_whatsoever/README.MD
flatten_any_dict_iterable_or_whatsoever/__init__.py
flatten_any_dict_iterable_or_whatsoever/requirements.txt
flatten_any_dict_iterable_or_whatsoever/thirdparty.json
flatten_any_dict_iterable_or_whatsoever-0.33.dist-info/LICENSE.rst
flatten_any_dict_iterable_or_whatsoever-0.33.dist-info/METADATA
flatten_any_dict_iterable_or_whatsoever-0.33.dist-info/WHEEL
flatten_any_dict_iterable_or_whatsoever-0.33.dist-info/top_level.txt
flatten_any_dict_iterable_or_whatsoever-0.33.dist-info/RECORD
